CHANGES
LICENSE
MANIFEST.in
README.rst
setup.py
django_event/__init__.py
django_event/admin.py
django_event/models.py
django_event/settings.py
django_event/utils.py
django_event.egg-info/PKG-INFO
django_event.egg-info/SOURCES.txt
django_event.egg-info/dependency_links.txt
django_event.egg-info/not-zip-safe
django_event.egg-info/requires.txt
django_event.egg-info/top_level.txt
django_event/backends/__init__.py
django_event/backends/selector.py
django_event/backends/base/__init__.py
django_event/backends/base/client.py
django_event/backends/base/publisher.py
django_event/backends/base/settings.py
django_event/backends/base/subscriber.py
django_event/backends/rabbitmq/__init__.py
django_event/backends/rabbitmq/client.py
django_event/backends/rabbitmq/publisher.py
django_event/backends/rabbitmq/settings.py
django_event/backends/rabbitmq/subscriber.py
django_event/backends/redis/__init__.py
django_event/backends/redis/client.py
django_event/backends/redis/publisher.py
django_event/backends/redis/settings.py
django_event/backends/redis/subscriber.py
django_event/management/__init__.py
django_event/management/commands/__init__.py
django_event/management/commands/deleteoldevents.py
django_event/management/commands/runwebsocketserver.py
django_event/management/commands/settings.py
django_event/migrations/0001_initial.py
django_event/migrations/0002_auto_20150519_1156.py
django_event/migrations/__init__.py
django_event/publisher/__init__.py
django_event/publisher/decorator.py
django_event/publisher/exceptions.py
django_event/publisher/request.py
django_event/publisher/urls.py
django_event/publisher/views.py
django_event/publisher/rest_framework/__init__.py
django_event/publisher/rest_framework/serializers.py
django_event/publisher/rest_framework/urls.py
django_event/publisher/rest_framework/views.py
django_event/subscriber/__init__.py
django_event/subscriber/connection.py
django_event/subscriber/listeners.py