Metadata-Version: 1.1
Name: django-event
Version: 1.0.3
Summary: Event notification system for django project
Home-page: https://github.com/ailove-dev/django-event
Author: Dmitry Panchenko
Author-email: d.panchenko@ailove.com
License: MIT
Platform: a
Platform: n
Platform: y
Classifier: Development Status :: 4 - Beta
Classifier: Development Status :: 5 - Production/Stable
Classifier: Environment :: Web Environment
Classifier: Framework :: Django
Classifier: Programming Language :: Python
Classifier: Programming Language :: Python :: 3
Classifier: Topic :: Utilities
